search_space/__init__.py
search_space/context_manager/__init__.py
search_space/context_manager/runtime_manager.py
search_space/context_manager/sampler_context.py
search_space/dsl/__init__.py
search_space/dsl/dsl_interface.py
search_space/errors/__init__.py
search_space/functions/__init__.py
search_space/functions/math.py
search_space/sampler/__init__.py
search_space/sampler/distribution_names.py
search_space/sampler/factory.py
search_space/sampler/default_implementations/__init__.py
search_space/sampler/default_implementations/bernoulli.py
search_space/sampler/default_implementations/uniform.py
search_space/spaces/__init__.py
search_space/spaces/search_space.py
search_space/spaces/search_space_protocol.py
search_space/spaces/asts/__init__.py
search_space/spaces/asts/constraints/__base__.py
search_space/spaces/asts/constraints/__init__.py
search_space/spaces/asts/constraints/__namespace__.py
search_space/spaces/asts/constraints/atoms.py
search_space/spaces/asts/constraints/cmp_ops.py
search_space/spaces/asts/constraints/expr_ops.py
search_space/spaces/asts/constraints/functions_and_predicates.py
search_space/spaces/asts/constraints/logic_ops.py
search_space/spaces/asts/constraints/segmentation_branch.py
search_space/spaces/asts/naturals_values/__base__.py
search_space/spaces/asts/naturals_values/__init__.py
search_space/spaces/asts/naturals_values/atoms.py
search_space/spaces/asts/naturals_values/expr_ops.py
search_space/spaces/asts/naturals_values/logic_ops.py
search_space/spaces/build_in_spaces/__init__.py
search_space/spaces/build_in_spaces/categorical_search_space.py
search_space/spaces/build_in_spaces/numeral_space.py
search_space/spaces/build_in_spaces/space_manager.py
search_space/spaces/build_in_spaces/tensor_space.py
search_space/spaces/domains/__base__.py
search_space/spaces/domains/__init__.py
search_space/spaces/domains/__namespace__.py
search_space/spaces/domains/bached_domain.py
search_space/spaces/domains/categorical_domain.py
py_search_space-1.0.7.dist-info/LICENSE
py_search_space-1.0.7.dist-info/METADATA
py_search_space-1.0.7.dist-info/WHEEL
py_search_space-1.0.7.dist-info/top_level.txt
py_search_space-1.0.7.dist-info/RECORD
